awslabs/__init__.py
awslabs/aws_diagram_mcp_server/__init__.py
awslabs/aws_diagram_mcp_server/diagrams_tools.py
awslabs/aws_diagram_mcp_server/models.py
awslabs/aws_diagram_mcp_server/scanner.py
awslabs/aws_diagram_mcp_server/server.py
awslabs_aws_diagram_mcp_server-1.0.17.dist-info/METADATA
awslabs_aws_diagram_mcp_server-1.0.17.dist-info/WHEEL
awslabs_aws_diagram_mcp_server-1.0.17.dist-info/entry_points.txt
awslabs_aws_diagram_mcp_server-1.0.17.dist-info/licenses/LICENSE
awslabs_aws_diagram_mcp_server-1.0.17.dist-info/licenses/NOTICE
awslabs_aws_diagram_mcp_server-1.0.17.dist-info/RECORD
