Metadata-Version: 2.4
Name: awslabs.aws-diagram-mcp-server
Version: 1.0.17
Summary: An MCP server that seamlessly creates diagrams using the Python diagrams package DSL
Project-URL: Homepage, https://awslabs.github.io/mcp/
Project-URL: Documentation, https://awslabs.github.io/mcp/servers/aws-diagram-mcp-server/
Project-URL: Source, https://github.com/awslabs/mcp.git
Project-URL: Bug Tracker, https://github.com/awslabs/mcp/issues
Project-URL: Changelog, https://github.com/awslabs/mcp/blob/main/src/aws-diagram-mcp-server/CHANGELOG.md
Author: Amazon Web Services
Author-email: AWSLabs MCP <203918161+awslabs-mcp@users.noreply.github.com>
License: Apache-2.0
License-File: LICENSE
License-File: NOTICE
Classifier: License :: OSI Approved :: Apache Software License
Classifier: Operating System :: OS Independent
Classifier: Programming Language :: Python
Classifier: Programming Language :: Python :: 3
Classifier: Programming Language :: Python :: 3.12
Classifier: Programming Language :: Python :: 3.13
Requires-Python: >=3.12
Requires-Dist: bandit>=1.8.6
Requires-Dist: boto3>=1.40.53
Requires-Dist: diagrams>=0.24.4
Requires-Dist: mcp[cli]>=1.23.0
Requires-Dist: pydantic>=2.12.2
Requires-Dist: sarif-om>=1.0.4
Requires-Dist: setuptools>=80.9.0
Requires-Dist: starlette>=0.48.0
Requires-Dist: urllib3>=2.5.0
